velodyn/__init__.py
velodyn/velocity_ci.py
velodyn/velocity_divergence.py
velodyn/velocity_dpst.py
velodyn/velocity_dynsys.py
velodyn-0.1.0.dist-info/LICENSE
velodyn-0.1.0.dist-info/METADATA
velodyn-0.1.0.dist-info/WHEEL
velodyn-0.1.0.dist-info/top_level.txt
velodyn-0.1.0.dist-info/RECORD
