Metadata-Version: 2.1
Name: velodyn
Version: 0.1.0
Summary: Dynamical systems approaches for RNA velocity analysis
Home-page: http://github.com/calico/velodyn
Author: Jacob C. Kimmel
Author-email: jacobkimmel@gmail.com
License: Apache
Platform: UNKNOWN
Classifier: Intended Audience :: Science/Research
Classifier: Topic :: Scientific/Engineering :: Bio-Informatics
Requires-Python: >=3.6
Requires-Dist: anndata (>=0.6.22.post1)
Requires-Dist: h5py (>=2.10.0)
Requires-Dist: loompy (>=2.0.16)
Requires-Dist: matplotlib (>=3.0.2)
Requires-Dist: numpy (>=1.17.4)
Requires-Dist: pandas (>=0.23.4)
Requires-Dist: scanpy (>=1.4)
Requires-Dist: scikit-learn (>=0.21.3)
Requires-Dist: scipy (>=1.2.0)
Requires-Dist: scvelo (>=0.1.16.dev41+74978dd)
Requires-Dist: seaborn (>=0.9.0)
Requires-Dist: pathos (>=0.2.5)
